[{
    "posada": "Cape fox",
    "disponibilidad": true,
    "ciudad": "Eksjö",
    "email": "jbeatey0@examiner.com",
    "id": "48b35aa2-c6bf-42de-b83a-e44d085035bd"
  }, {
    "posada": "Rhinoceros, black",
    "disponibilidad": false,
    "ciudad": "Lyambir’",
    "email": "sloker1@weather.com",
    "id": "a91354ec-1910-477a-aa9e-4cbdd6682f46"
  }, {
    "posada": "Crane, stanley",
    "disponibilidad": false,
    "ciudad": "Sembungan Kidul",
    "email": "nreadie2@so-net.ne.jp",
    "id": "0773f1d6-fc4b-4413-a4d4-1b3600ab5852"
  }, {
    "posada": "Mandras tree shrew",
    "disponibilidad": false,
    "ciudad": "Växjö",
    "email": "blapere3@thetimes.co.uk",
    "id": "9e8b175a-df52-4ac0-ba2e-26bbab33e7bd"
  }, {
    "posada": "Phalarope, grey",
    "disponibilidad": true,
    "ciudad": "Gunungmanik",
    "email": "tohearn4@ed.gov",
    "id": "a80d9a87-af7f-4b3f-9f8a-7db5f82279ca"
  }, {
    "posada": "Jackal, black-backed",
    "disponibilidad": false,
    "ciudad": "Lindi",
    "email": "gbursnall5@jalbum.net",
    "id": "2d508878-41ef-4302-9b96-347a4aff6603"
  }, {
    "posada": "Stone sheep",
    "disponibilidad": true,
    "ciudad": "Anyar",
    "email": "hblodg6@squarespace.com",
    "id": "71dde1f6-4dd9-4c70-aecc-fd6b4e66a23a"
  }, {
    "posada": "Impala",
    "disponibilidad": true,
    "ciudad": "Pakel",
    "email": "jtraite7@engadget.com",
    "id": "ef0fc1bb-143e-425f-a1c6-4d058e53f99a"
  }, {
    "posada": "Bird, secretary",
    "disponibilidad": false,
    "ciudad": "Saaban",
    "email": "gpalser8@tiny.cc",
    "id": "c86cf7e5-92b0-4ea5-8358-3ec514d7865d"
  }, {
    "posada": "Mouflon",
    "disponibilidad": false,
    "ciudad": "Agogo",
    "email": "bcrosoer9@japanpost.jp",
    "id": "70514b2b-b51d-4144-9d67-79b199f05c76"
  }, {
    "posada": "Fowl, helmeted guinea",
    "disponibilidad": true,
    "ciudad": "Tanggan",
    "email": "kwytcharda@imageshack.us",
    "id": "7ac77deb-460b-4990-be0a-545a4a75edda"
  }, {
    "posada": "Boubou, southern",
    "disponibilidad": false,
    "ciudad": "San Buenaventura",
    "email": "dferronib@youku.com",
    "id": "1feaf2b5-79c0-4b87-b53f-2e8207aacc04"
  }, {
    "posada": "Common green iguana",
    "disponibilidad": false,
    "ciudad": "Prosvet",
    "email": "vcatchesidec@washington.edu",
    "id": "44d06047-341c-43f2-80c0-a5909a870f13"
  }, {
    "posada": "Mockingbird, galapagos",
    "disponibilidad": false,
    "ciudad": "Oxelösund",
    "email": "ckneed@newsvine.com",
    "id": "7f76eec4-942f-46a4-9a94-e53594880ef0"
  }, {
    "posada": "Campo flicker",
    "disponibilidad": true,
    "ciudad": "Mahaba",
    "email": "iskunee@mit.edu",
    "id": "923f8c56-936b-4799-be65-227e287fda53"
  }, {
    "posada": "Dusky rattlesnake",
    "disponibilidad": false,
    "ciudad": "Vilar do Monte",
    "email": "tstockmanf@newyorker.com",
    "id": "3edd4efb-4c40-44bf-a761-7f7d9fc9f0a3"
  }, {
    "posada": "Wallaby, river",
    "disponibilidad": false,
    "ciudad": "Minas",
    "email": "jcourceyg@yandex.ru",
    "id": "54224689-d43b-4cbd-9bc3-6b75888b8d20"
  }, {
    "posada": "Asian red fox",
    "disponibilidad": true,
    "ciudad": "Chambly",
    "email": "agarreltsh@nbcnews.com",
    "id": "82be44d2-68ec-47c9-82cc-c8f826848737"
  }, {
    "posada": "Antelope, sable",
    "disponibilidad": true,
    "ciudad": "Puerto Barrios",
    "email": "gparfreyi@fotki.com",
    "id": "16dafbd4-84f7-4c69-9363-c83c39b30ccb"
  }, {
    "posada": "Paca",
    "disponibilidad": true,
    "ciudad": "Wuquan",
    "email": "slapsleyj@oakley.com",
    "id": "80139dee-877e-4393-ad36-b853a180b574"
  }, {
    "posada": "Crab, sally lightfoot",
    "disponibilidad": false,
    "ciudad": "Juliaca",
    "email": "fmittenk@hud.gov",
    "id": "dcd524e8-935d-4df2-bc3b-f33713017eda"
  }, {
    "posada": "Two-banded monitor",
    "disponibilidad": false,
    "ciudad": "Jiguan",
    "email": "kmclisel@bloglovin.com",
    "id": "a978db3c-9787-4ba7-8114-5d1b076aa27b"
  }, {
    "posada": "Dove, white-winged",
    "disponibilidad": false,
    "ciudad": "Balucawi",
    "email": "jstuerm@macromedia.com",
    "id": "e9080d52-b129-47b8-8084-442c36664b55"
  }, {
    "posada": "Eurasian hoopoe",
    "disponibilidad": false,
    "ciudad": "Bibis",
    "email": "bstapfordn@berkeley.edu",
    "id": "f7339789-6be9-44c6-9b63-183d92b83d49"
  }, {
    "posada": "Nelson ground squirrel",
    "disponibilidad": true,
    "ciudad": "Dawuhan",
    "email": "jcapeo@histats.com",
    "id": "704c2d42-b56e-4013-972c-c3b18484a801"
  }, {
    "posada": "White-rumped vulture",
    "disponibilidad": true,
    "ciudad": "Káto Glikóvrisi",
    "email": "cmorap@eepurl.com",
    "id": "6601e41b-a0ab-4b1b-85c0-f3852b6b8592"
  }, {
    "posada": "Deer, savannah",
    "disponibilidad": false,
    "ciudad": "Buenavista",
    "email": "lshalcrosq@weebly.com",
    "id": "b4a8234b-3183-4075-8f15-02c500b0f186"
  }, {
    "posada": "Lesser flamingo",
    "disponibilidad": false,
    "ciudad": "Date",
    "email": "dmelloir@imgur.com",
    "id": "e499516c-5d5c-48b4-81fd-a5957a0cfee8"
  }, {
    "posada": "Lion, steller's sea",
    "disponibilidad": false,
    "ciudad": "Si Mahosot",
    "email": "swickendons@ft.com",
    "id": "a4e75d51-a4e7-4a35-a701-59367be9b736"
  }, {
    "posada": "Wattled crane",
    "disponibilidad": false,
    "ciudad": "Pali",
    "email": "ajammett@nbcnews.com",
    "id": "fef4ac8a-4156-4d59-bacd-3ca22d833d26"
  }]
  